mptc/ColouredStrings.py
mptc/__init__.py
mptc/cleanup.py
mptc/mptc.py
mptc/newfile.py
mptc/simplelog.py
mptc/templates.py
mptc-0.2.0.dist-info/LICENSE.txt
mptc-0.2.0.dist-info/METADATA
mptc-0.2.0.dist-info/WHEEL
mptc-0.2.0.dist-info/top_level.txt
mptc-0.2.0.dist-info/RECORD
