Metadata-Version: 2.1
Name: mptc
Version: 0.2.0
Summary: a small toolkit of functions i use
Home-page: https://github.com/Th3M4ttman/mptc
Author: Th3M4ttman
Author-email: WorkMatthewJHarros94@gmail.com
License: UNKNOWN
Platform: UNKNOWN
Classifier: Programming Language :: Python :: 3
Classifier: License :: OSI Approved :: MIT License
Classifier: Operating System :: OS Independent
Requires-Python: >=3.6
License-File: LICENSE.txt
